auto_cli/__init__.py
auto_cli/cli.py
auto_cli_py-0.4.6.dist-info/LICENSE
auto_cli_py-0.4.6.dist-info/METADATA
auto_cli_py-0.4.6.dist-info/WHEEL
auto_cli_py-0.4.6.dist-info/top_level.txt
auto_cli_py-0.4.6.dist-info/RECORD
