Metadata-Version: 2.1
Name: auto-cli-py
Version: 0.4.6
Summary: auto-cli-py: python package to automatically create CLI commands from function via introspection
Home-page: http://github.com/tangledpath/auto-cli-py
Author: Steven Miers
Author-email: steven.miers@gmail.com
License: UNKNOWN
Platform: UNKNOWN
Classifier: Programming Language :: Python :: 3
Classifier: License :: OSI Approved :: MIT License
Classifier: Operating System :: OS Independent
Requires-Python: >=3.6
